{"expireTime":9007200872647810000,"key":"gatsby-plugin-mdx-entire-payload-75b34e5a83c757f8044875b99c5c4c4a-","val":{"mdast":{"type":"root","children":[{"type":"import","value":"import DefaultLayout from \"/home/michele/Projects/Eduzz/houston/node_modules/gatsby-theme-docz/src/base/Layout.js\"","position":{"start":{"line":3,"column":1,"offset":2},"end":{"line":3,"column":115,"offset":116},"indent":[]}},{"type":"export","default":true,"value":"export default DefaultLayout","position":{"start":{"line":5,"column":1,"offset":118},"end":{"line":5,"column":29,"offset":146},"indent":[]}},{"type":"import","value":"import { Playground } from 'docz';","position":{"start":{"line":8,"column":1,"offset":149},"end":{"line":8,"column":35,"offset":183},"indent":[]}},{"type":"import","value":"import Table from './';","position":{"start":{"line":10,"column":1,"offset":185},"end":{"line":10,"column":24,"offset":208},"indent":[]}},{"type":"heading","depth":2,"children":[{"type":"text","value":"Tabela","position":{"start":{"line":12,"column":4,"offset":213},"end":{"line":12,"column":10,"offset":219},"indent":[]}}],"position":{"start":{"line":12,"column":1,"offset":210},"end":{"line":12,"column":10,"offset":219},"indent":[]}},{"type":"paragraph","children":[{"type":"text","value":"Tabelas apresentam informações de uma forma fácil de visualizar, de modo que os usuários podem\nprocurar por padrões e percepções.","position":{"start":{"line":14,"column":1,"offset":221},"end":{"line":15,"column":35,"offset":350},"indent":[1]}}],"position":{"start":{"line":14,"column":1,"offset":221},"end":{"line":15,"column":35,"offset":350},"indent":[1]}},{"type":"heading","depth":2,"children":[{"type":"text","value":"Tabela simples","position":{"start":{"line":17,"column":4,"offset":355},"end":{"line":17,"column":18,"offset":369},"indent":[]}}],"position":{"start":{"line":17,"column":1,"offset":352},"end":{"line":17,"column":18,"offset":369},"indent":[]}},{"type":"jsx","value":"<Playground>\n  <Table>\n    <Table.Column field='id' label='ID' />\n    <Table.Column field='product' label='Produto' />\n    <Table.Column field='owner' label='Produtor' />\n    <Table.Column field='value' label='Valor' align='right' />\n    <Table.Row>\n      <Table.Cell>1</Table.Cell>\n      <Table.Cell>Produto teste</Table.Cell>\n      <Table.Cell>John Doe</Table.Cell>\n      <Table.Cell align='right'>R$ 120,00</Table.Cell>\n    </Table.Row>\n    <Table.Row>\n      <Table.Cell>2</Table.Cell>\n      <Table.Cell>Produto teste</Table.Cell>\n      <Table.Cell>John Doe</Table.Cell>\n      <Table.Cell align='right'>R$ 100,00</Table.Cell>\n    </Table.Row>\n    <Table.Row>\n      <Table.Cell>3</Table.Cell>\n      <Table.Cell>Produto teste</Table.Cell>\n      <Table.Cell>John Doe</Table.Cell>\n      <Table.Cell align='right'>R$ 200,20</Table.Cell>\n    </Table.Row>\n  </Table>\n</Playground>","position":{"start":{"line":19,"column":1,"offset":371},"end":{"line":44,"column":14,"offset":1247},"indent":[1,1,1,1,1,1,1,1,1,1,1,1,1,1,1,1,1,1,1,1,1,1,1,1,1]}},{"type":"heading","depth":2,"children":[{"type":"text","value":"Tabela com paginação","position":{"start":{"line":46,"column":4,"offset":1252},"end":{"line":46,"column":24,"offset":1272},"indent":[]}}],"position":{"start":{"line":46,"column":1,"offset":1249},"end":{"line":46,"column":24,"offset":1272},"indent":[]}},{"type":"jsx","value":"<Playground>\n  <Table>\n    <Table.Column field='id' label='ID' />\n    <Table.Column field='product' label='Produto' />\n    <Table.Column field='owner' label='Produtor' />\n    <Table.Column field='value' label='Valor' align='right' />\n    <Table.Row>\n      <Table.Cell>1</Table.Cell>\n      <Table.Cell>Produto teste</Table.Cell>\n      <Table.Cell>John Doe</Table.Cell>\n      <Table.Cell align='right'>R$ 120,00</Table.Cell>\n    </Table.Row>\n    <Table.Row>\n      <Table.Cell>2</Table.Cell>\n      <Table.Cell>Produto teste</Table.Cell>\n      <Table.Cell>John Doe</Table.Cell>\n      <Table.Cell align='right'>R$ 100,00</Table.Cell>\n    </Table.Row>\n    <Table.Row>\n      <Table.Cell>3</Table.Cell>\n      <Table.Cell>Produto teste</Table.Cell>\n      <Table.Cell>John Doe</Table.Cell>\n      <Table.Cell align='right'>R$ 200,20</Table.Cell>\n    </Table.Row>\n    <Table.Pagination page={1} perPage={5} total={20} onChangePage={page => console.log(page)} />\n  </Table>\n</Playground>","position":{"start":{"line":48,"column":1,"offset":1274},"end":{"line":74,"column":14,"offset":2248},"indent":[1,1,1,1,1,1,1,1,1,1,1,1,1,1,1,1,1,1,1,1,1,1,1,1,1,1]}},{"type":"heading","depth":2,"children":[{"type":"text","value":"Tabela com ações","position":{"start":{"line":76,"column":4,"offset":2253},"end":{"line":76,"column":20,"offset":2269},"indent":[]}}],"position":{"start":{"line":76,"column":1,"offset":2250},"end":{"line":76,"column":20,"offset":2269},"indent":[]}},{"type":"jsx","value":"<Playground>\n  <Table>\n    <Table.Column field='id' label='ID' />\n    <Table.Column field='product' label='Produto' />\n    <Table.Column field='owner' label='Produtor' />\n    <Table.Column field='value' label='Valor' align='right' />\n    <Table.Row data={{ id: 1, product: 'Produto teste ' }}>\n      <Table.Cell>1</Table.Cell>\n      <Table.Cell>Produto teste</Table.Cell>\n      <Table.Cell>John Doe</Table.Cell>\n      <Table.Cell align='right'>R$ 120,00</Table.Cell>\n    </Table.Row>\n    <Table.Row data={{ id: 2, product: 'Produto teste ' }}>\n      <Table.Cell>2</Table.Cell>\n      <Table.Cell>Produto teste</Table.Cell>\n      <Table.Cell>John Doe</Table.Cell>\n      <Table.Cell align='right'>R$ 100,00</Table.Cell>\n    </Table.Row>\n    <Table.Row data={{ id: 3, product: 'Produto teste ' }}>\n      <Table.Cell>3</Table.Cell>\n      <Table.Cell>Produto teste</Table.Cell>\n      <Table.Cell>John Doe</Table.Cell>\n      <Table.Cell align='right'>R$ 200,20</Table.Cell>\n      <Table.Actions>\n        <Table.Option>Ação especial</Table.Option>\n        <Table.Option>Editar</Table.Option>\n        <Table.Option>Remover</Table.Option>\n      </Table.Actions>\n    </Table.Row>\n    <Table.Actions align='right' label='*'>\n      <Table.Option onClick={row => console.log(row)}>Editar</Table.Option>\n      <Table.Option>Remover</Table.Option>\n    </Table.Actions>\n  </Table>\n</Playground>","position":{"start":{"line":78,"column":1,"offset":2271},"end":{"line":112,"column":14,"offset":3648},"indent":[1,1,1,1,1,1,1,1,1,1,1,1,1,1,1,1,1,1,1,1,1,1,1,1,1,1,1,1,1,1,1,1,1,1]}},{"type":"heading","depth":2,"children":[{"type":"text","value":"Tabela com ordenação","position":{"start":{"line":114,"column":4,"offset":3653},"end":{"line":114,"column":24,"offset":3673},"indent":[]}}],"position":{"start":{"line":114,"column":1,"offset":3650},"end":{"line":114,"column":24,"offset":3673},"indent":[]}},{"type":"jsx","value":"<Playground>\n  <Table onSortable={ordenation => console.log(ordenation)}>\n    <Table.Column field='id' label='ID' />\n    <Table.Column field='product' label='Produto' sortable />\n    <Table.Column field='owner' label='Produtor' sortable />\n    <Table.Column field='value' label='Valor' align='right' />\n    <Table.Row>\n      <Table.Cell>1</Table.Cell>\n      <Table.Cell>Produto teste 1</Table.Cell>\n      <Table.Cell>John Doe</Table.Cell>\n      <Table.Cell align='right'>R$ 120,00</Table.Cell>\n    </Table.Row>\n    <Table.Row>\n      <Table.Cell>2</Table.Cell>\n      <Table.Cell>Produto teste 2</Table.Cell>\n      <Table.Cell>John Doe</Table.Cell>\n      <Table.Cell align='right'>R$ 100,00</Table.Cell>\n    </Table.Row>\n    <Table.Row>\n      <Table.Cell>3</Table.Cell>\n      <Table.Cell>Produto teste 3</Table.Cell>\n      <Table.Cell>John Doe</Table.Cell>\n      <Table.Cell align='right'>R$ 200,20</Table.Cell>\n    </Table.Row>\n  </Table>\n</Playground>","position":{"start":{"line":116,"column":1,"offset":3675},"end":{"line":141,"column":14,"offset":4626},"indent":[1,1,1,1,1,1,1,1,1,1,1,1,1,1,1,1,1,1,1,1,1,1,1,1,1]}},{"type":"heading","depth":2,"children":[{"type":"text","value":"Tabela com collapse","position":{"start":{"line":143,"column":4,"offset":4631},"end":{"line":143,"column":23,"offset":4650},"indent":[]}}],"position":{"start":{"line":143,"column":1,"offset":4628},"end":{"line":143,"column":23,"offset":4650},"indent":[]}},{"type":"jsx","value":"<Playground>\n  <Table>\n    <Table.Column field='id' label='ID' />\n    <Table.Column field='product' label='Produto' />\n    <Table.Column field='owner' label='Produtor' />\n    <Table.Column field='value' label='Valor' align='right' />\n    <Table.Row>\n      <Table.Cell>1</Table.Cell>\n      <Table.Cell>Produto teste</Table.Cell>\n      <Table.Cell>John Doe</Table.Cell>\n      <Table.Cell align='right'>R$ 120,00</Table.Cell>\n    </Table.Row>\n    <Table.Row data={{ id: 2, product: 'Produto teste' }}>\n      <Table.Cell>2</Table.Cell>\n      <Table.Cell>Produto teste</Table.Cell>\n      <Table.Cell>John Doe</Table.Cell>\n      <Table.Cell align='right'>R$ 100,00</Table.Cell>\n      <Table.Collapse>\n        <Table.Column field='date' label='Data' />\n        <Table.Column field='sales' label='Vendas' />\n        <Table.Row>\n          <Table.Cell>29/03</Table.Cell>\n          <Table.Cell>20 vendas</Table.Cell>\n        </Table.Row>\n        <Table.Row>\n          <Table.Cell>28/03</Table.Cell>\n          <Table.Cell>170 vendas</Table.Cell>\n        </Table.Row>\n      </Table.Collapse>\n    </Table.Row>\n    <Table.Row>\n      <Table.Cell>3</Table.Cell>\n      <Table.Cell>Produto teste</Table.Cell>\n      <Table.Cell>John Doe</Table.Cell>\n      <Table.Cell align='right'>R$ 200,20</Table.Cell>\n    </Table.Row>\n  </Table>\n</Playground>","position":{"start":{"line":145,"column":1,"offset":4652},"end":{"line":182,"column":14,"offset":5978},"indent":[1,1,1,1,1,1,1,1,1,1,1,1,1,1,1,1,1,1,1,1,1,1,1,1,1,1,1,1,1,1,1,1,1,1,1,1,1]}},{"type":"heading","depth":2,"children":[{"type":"text","value":"Propriedades da Table.Column","position":{"start":{"line":184,"column":4,"offset":5983},"end":{"line":184,"column":32,"offset":6011},"indent":[]}}],"position":{"start":{"line":184,"column":1,"offset":5980},"end":{"line":184,"column":32,"offset":6011},"indent":[]}},{"type":"paragraph","children":[{"type":"text","value":"Usando tabela do próprio markdown","position":{"start":{"line":186,"column":1,"offset":6013},"end":{"line":186,"column":34,"offset":6046},"indent":[]}}],"position":{"start":{"line":186,"column":1,"offset":6013},"end":{"line":186,"column":34,"offset":6046},"indent":[]}},{"type":"table","align":[null,null,null,null,null],"children":[{"type":"tableRow","children":[{"type":"tableCell","children":[{"type":"text","value":"prop","position":{"start":{"line":188,"column":3,"offset":6050},"end":{"line":188,"column":7,"offset":6054},"indent":[]}}],"position":{"start":{"line":188,"column":3,"offset":6050},"end":{"line":188,"column":11,"offset":6058},"indent":[]}},{"type":"tableCell","children":[{"type":"text","value":"tipo","position":{"start":{"line":188,"column":14,"offset":6061},"end":{"line":188,"column":18,"offset":6065},"indent":[]}}],"position":{"start":{"line":188,"column":14,"offset":6061},"end":{"line":188,"column":31,"offset":6078},"indent":[]}},{"type":"tableCell","children":[{"type":"text","value":"obrigatório","position":{"start":{"line":188,"column":34,"offset":6081},"end":{"line":188,"column":45,"offset":6092},"indent":[]}}],"position":{"start":{"line":188,"column":34,"offset":6081},"end":{"line":188,"column":45,"offset":6092},"indent":[]}},{"type":"tableCell","children":[{"type":"text","value":"padrão","position":{"start":{"line":188,"column":48,"offset":6095},"end":{"line":188,"column":54,"offset":6101},"indent":[]}}],"position":{"start":{"line":188,"column":48,"offset":6095},"end":{"line":188,"column":55,"offset":6102},"indent":[]}},{"type":"tableCell","children":[{"type":"text","value":"descrição","position":{"start":{"line":188,"column":58,"offset":6105},"end":{"line":188,"column":67,"offset":6114},"indent":[]}}],"position":{"start":{"line":188,"column":58,"offset":6105},"end":{"line":188,"column":150,"offset":6197},"indent":[]}}],"position":{"start":{"line":188,"column":1,"offset":6048},"end":{"line":188,"column":152,"offset":6199},"indent":[]}},{"type":"tableRow","children":[{"type":"tableCell","children":[{"type":"text","value":"field","position":{"start":{"line":190,"column":3,"offset":6354},"end":{"line":190,"column":8,"offset":6359},"indent":[]}}],"position":{"start":{"line":190,"column":3,"offset":6354},"end":{"line":190,"column":11,"offset":6362},"indent":[]}},{"type":"tableCell","children":[{"type":"inlineCode","value":"string","position":{"start":{"line":190,"column":14,"offset":6365},"end":{"line":190,"column":22,"offset":6373},"indent":[]}}],"position":{"start":{"line":190,"column":14,"offset":6365},"end":{"line":190,"column":31,"offset":6382},"indent":[]}},{"type":"tableCell","children":[{"type":"text","value":"true","position":{"start":{"line":190,"column":34,"offset":6385},"end":{"line":190,"column":38,"offset":6389},"indent":[]}}],"position":{"start":{"line":190,"column":34,"offset":6385},"end":{"line":190,"column":45,"offset":6396},"indent":[]}},{"type":"tableCell","children":[{"type":"text","value":"-","position":{"start":{"line":190,"column":48,"offset":6399},"end":{"line":190,"column":49,"offset":6400},"indent":[]}}],"position":{"start":{"line":190,"column":48,"offset":6399},"end":{"line":190,"column":55,"offset":6406},"indent":[]}},{"type":"tableCell","children":[{"type":"text","value":"Chave única.","position":{"start":{"line":190,"column":58,"offset":6409},"end":{"line":190,"column":70,"offset":6421},"indent":[]}}],"position":{"start":{"line":190,"column":58,"offset":6409},"end":{"line":190,"column":150,"offset":6501},"indent":[]}}],"position":{"start":{"line":190,"column":1,"offset":6352},"end":{"line":190,"column":152,"offset":6503},"indent":[]}},{"type":"tableRow","children":[{"type":"tableCell","children":[{"type":"text","value":"label","position":{"start":{"line":191,"column":3,"offset":6506},"end":{"line":191,"column":8,"offset":6511},"indent":[]}}],"position":{"start":{"line":191,"column":3,"offset":6506},"end":{"line":191,"column":11,"offset":6514},"indent":[]}},{"type":"tableCell","children":[{"type":"inlineCode","value":"React.ReactNode","position":{"start":{"line":191,"column":14,"offset":6517},"end":{"line":191,"column":31,"offset":6534},"indent":[]}}],"position":{"start":{"line":191,"column":14,"offset":6517},"end":{"line":191,"column":31,"offset":6534},"indent":[]}},{"type":"tableCell","children":[{"type":"text","value":"true","position":{"start":{"line":191,"column":34,"offset":6537},"end":{"line":191,"column":38,"offset":6541},"indent":[]}}],"position":{"start":{"line":191,"column":34,"offset":6537},"end":{"line":191,"column":45,"offset":6548},"indent":[]}},{"type":"tableCell","children":[{"type":"text","value":"-","position":{"start":{"line":191,"column":48,"offset":6551},"end":{"line":191,"column":49,"offset":6552},"indent":[]}}],"position":{"start":{"line":191,"column":48,"offset":6551},"end":{"line":191,"column":55,"offset":6558},"indent":[]}},{"type":"tableCell","children":[{"type":"text","value":"-","position":{"start":{"line":191,"column":58,"offset":6561},"end":{"line":191,"column":59,"offset":6562},"indent":[]}}],"position":{"start":{"line":191,"column":58,"offset":6561},"end":{"line":191,"column":150,"offset":6653},"indent":[]}}],"position":{"start":{"line":191,"column":1,"offset":6504},"end":{"line":191,"column":152,"offset":6655},"indent":[]}},{"type":"tableRow","children":[{"type":"tableCell","children":[{"type":"text","value":"width","position":{"start":{"line":192,"column":3,"offset":6658},"end":{"line":192,"column":8,"offset":6663},"indent":[]}}],"position":{"start":{"line":192,"column":3,"offset":6658},"end":{"line":192,"column":11,"offset":6666},"indent":[]}},{"type":"tableCell","children":[{"type":"inlineCode","value":"number","position":{"start":{"line":192,"column":14,"offset":6669},"end":{"line":192,"column":22,"offset":6677},"indent":[]}}],"position":{"start":{"line":192,"column":14,"offset":6669},"end":{"line":192,"column":31,"offset":6686},"indent":[]}},{"type":"tableCell","children":[{"type":"text","value":"false","position":{"start":{"line":192,"column":34,"offset":6689},"end":{"line":192,"column":39,"offset":6694},"indent":[]}}],"position":{"start":{"line":192,"column":34,"offset":6689},"end":{"line":192,"column":45,"offset":6700},"indent":[]}},{"type":"tableCell","children":[{"type":"text","value":"-","position":{"start":{"line":192,"column":48,"offset":6703},"end":{"line":192,"column":49,"offset":6704},"indent":[]}}],"position":{"start":{"line":192,"column":48,"offset":6703},"end":{"line":192,"column":55,"offset":6710},"indent":[]}},{"type":"tableCell","children":[{"type":"text","value":"-","position":{"start":{"line":192,"column":58,"offset":6713},"end":{"line":192,"column":59,"offset":6714},"indent":[]}}],"position":{"start":{"line":192,"column":58,"offset":6713},"end":{"line":192,"column":150,"offset":6805},"indent":[]}}],"position":{"start":{"line":192,"column":1,"offset":6656},"end":{"line":192,"column":152,"offset":6807},"indent":[]}},{"type":"tableRow","children":[{"type":"tableCell","children":[{"type":"text","value":"align","position":{"start":{"line":193,"column":3,"offset":6810},"end":{"line":193,"column":8,"offset":6815},"indent":[]}}],"position":{"start":{"line":193,"column":3,"offset":6810},"end":{"line":193,"column":11,"offset":6818},"indent":[]}},{"type":"tableCell","children":[{"type":"inlineCode","value":"ITableAlign","position":{"start":{"line":193,"column":14,"offset":6821},"end":{"line":193,"column":27,"offset":6834},"indent":[]}}],"position":{"start":{"line":193,"column":14,"offset":6821},"end":{"line":193,"column":31,"offset":6838},"indent":[]}},{"type":"tableCell","children":[{"type":"text","value":"false","position":{"start":{"line":193,"column":34,"offset":6841},"end":{"line":193,"column":39,"offset":6846},"indent":[]}}],"position":{"start":{"line":193,"column":34,"offset":6841},"end":{"line":193,"column":45,"offset":6852},"indent":[]}},{"type":"tableCell","children":[{"type":"inlineCode","value":"left","position":{"start":{"line":193,"column":48,"offset":6855},"end":{"line":193,"column":54,"offset":6861},"indent":[]}}],"position":{"start":{"line":193,"column":48,"offset":6855},"end":{"line":193,"column":55,"offset":6862},"indent":[]}},{"type":"tableCell","children":[{"type":"text","value":"-","position":{"start":{"line":193,"column":58,"offset":6865},"end":{"line":193,"column":59,"offset":6866},"indent":[]}}],"position":{"start":{"line":193,"column":58,"offset":6865},"end":{"line":193,"column":150,"offset":6957},"indent":[]}}],"position":{"start":{"line":193,"column":1,"offset":6808},"end":{"line":193,"column":152,"offset":6959},"indent":[]}},{"type":"tableRow","children":[{"type":"tableCell","children":[{"type":"text","value":"sortable","position":{"start":{"line":194,"column":3,"offset":6962},"end":{"line":194,"column":11,"offset":6970},"indent":[]}}],"position":{"start":{"line":194,"column":3,"offset":6962},"end":{"line":194,"column":11,"offset":6970},"indent":[]}},{"type":"tableCell","children":[{"type":"inlineCode","value":"boolean","position":{"start":{"line":194,"column":14,"offset":6973},"end":{"line":194,"column":23,"offset":6982},"indent":[]}}],"position":{"start":{"line":194,"column":14,"offset":6973},"end":{"line":194,"column":31,"offset":6990},"indent":[]}},{"type":"tableCell","children":[{"type":"text","value":"false","position":{"start":{"line":194,"column":34,"offset":6993},"end":{"line":194,"column":39,"offset":6998},"indent":[]}}],"position":{"start":{"line":194,"column":34,"offset":6993},"end":{"line":194,"column":45,"offset":7004},"indent":[]}},{"type":"tableCell","children":[{"type":"inlineCode","value":"false","position":{"start":{"line":194,"column":48,"offset":7007},"end":{"line":194,"column":55,"offset":7014},"indent":[]}}],"position":{"start":{"line":194,"column":48,"offset":7007},"end":{"line":194,"column":55,"offset":7014},"indent":[]}},{"type":"tableCell","children":[{"type":"text","value":"Quando ","position":{"start":{"line":194,"column":58,"offset":7017},"end":{"line":194,"column":65,"offset":7024},"indent":[]}},{"type":"inlineCode","value":"true","position":{"start":{"line":194,"column":65,"offset":7024},"end":{"line":194,"column":71,"offset":7030},"indent":[]}},{"type":"text","value":", ao clicar na coluna, chama a função","position":{"start":{"line":194,"column":71,"offset":7030},"end":{"line":194,"column":108,"offset":7067},"indent":[]}},{"type":"inlineCode","value":" onSortable","position":{"start":{"line":194,"column":108,"offset":7067},"end":{"line":194,"column":121,"offset":7080},"indent":[]}},{"type":"text","value":" passando o ","position":{"start":{"line":194,"column":121,"offset":7080},"end":{"line":194,"column":133,"offset":7092},"indent":[]}},{"type":"inlineCode","value":"field","position":{"start":{"line":194,"column":133,"offset":7092},"end":{"line":194,"column":140,"offset":7099},"indent":[]}},{"type":"text","value":" e o sort.","position":{"start":{"line":194,"column":140,"offset":7099},"end":{"line":194,"column":150,"offset":7109},"indent":[]}}],"position":{"start":{"line":194,"column":58,"offset":7017},"end":{"line":194,"column":150,"offset":7109},"indent":[]}}],"position":{"start":{"line":194,"column":1,"offset":6960},"end":{"line":194,"column":152,"offset":7111},"indent":[]}}],"position":{"start":{"line":188,"column":1,"offset":6048},"end":{"line":194,"column":152,"offset":7111},"indent":[1,1,1,1,1,1]}},{"type":"export","value":"export const _frontmatter = {}","position":{"start":{"line":197,"column":1,"offset":7114},"end":{"line":197,"column":31,"offset":7144},"indent":[]}}],"position":{"start":{"line":1,"column":1,"offset":0},"end":{"line":197,"column":31,"offset":7144}}},"scopeImports":[],"scopeIdentifiers":[],"rawMDXOutput":"/* @jsx mdx */\nimport { mdx } from '@mdx-js/react';\n/* @jsxRuntime classic */\n/* @jsx mdx */\nimport DefaultLayout from \"/home/michele/Projects/Eduzz/houston/node_modules/gatsby-theme-docz/src/base/Layout.js\"\nimport { Playground } from 'docz';\nimport Table from './';\nexport const _frontmatter = {};\n\nconst layoutProps = {\n  _frontmatter\n};\nconst MDXLayout = DefaultLayout\nexport default function MDXContent({\n  components,\n  ...props\n}) {\n  return <MDXLayout {...layoutProps} {...props} components={components} mdxType=\"MDXLayout\">\n\n\n\n\n    <h2 {...{\n      \"id\": \"tabela\"\n    }}>{`Tabela`}</h2>\n    <p>{`Tabelas apresentam informações de uma forma fácil de visualizar, de modo que os usuários podem\nprocurar por padrões e percepções.`}</p>\n    <h2 {...{\n      \"id\": \"tabela-simples\"\n    }}>{`Tabela simples`}</h2>\n    <Playground __position={0} __code={'<Table>\\n  <Table.Column field=\\\"id\\\" label=\\\"ID\\\" />\\n  <Table.Column field=\\\"product\\\" label=\\\"Produto\\\" />\\n  <Table.Column field=\\\"owner\\\" label=\\\"Produtor\\\" />\\n  <Table.Column field=\\\"value\\\" label=\\\"Valor\\\" align=\\\"right\\\" />\\n  <Table.Row>\\n    <Table.Cell>1</Table.Cell>\\n    <Table.Cell>Produto teste</Table.Cell>\\n    <Table.Cell>John Doe</Table.Cell>\\n    <Table.Cell align=\\\"right\\\">R$ 120,00</Table.Cell>\\n  </Table.Row>\\n  <Table.Row>\\n    <Table.Cell>2</Table.Cell>\\n    <Table.Cell>Produto teste</Table.Cell>\\n    <Table.Cell>John Doe</Table.Cell>\\n    <Table.Cell align=\\\"right\\\">R$ 100,00</Table.Cell>\\n  </Table.Row>\\n  <Table.Row>\\n    <Table.Cell>3</Table.Cell>\\n    <Table.Cell>Produto teste</Table.Cell>\\n    <Table.Cell>John Doe</Table.Cell>\\n    <Table.Cell align=\\\"right\\\">R$ 200,20</Table.Cell>\\n  </Table.Row>\\n</Table>'} __scope={{\n      props,\n      DefaultLayout,\n      Playground,\n      Table,\n      DefaultLayout,\n      _frontmatter\n    }} mdxType=\"Playground\">\n  <Table mdxType=\"Table\">\n    <Table.Column field='id' label='ID' />\n    <Table.Column field='product' label='Produto' />\n    <Table.Column field='owner' label='Produtor' />\n    <Table.Column field='value' label='Valor' align='right' />\n    <Table.Row>\n      <Table.Cell>1</Table.Cell>\n      <Table.Cell>Produto teste</Table.Cell>\n      <Table.Cell>John Doe</Table.Cell>\n      <Table.Cell align='right'>R$ 120,00</Table.Cell>\n    </Table.Row>\n    <Table.Row>\n      <Table.Cell>2</Table.Cell>\n      <Table.Cell>Produto teste</Table.Cell>\n      <Table.Cell>John Doe</Table.Cell>\n      <Table.Cell align='right'>R$ 100,00</Table.Cell>\n    </Table.Row>\n    <Table.Row>\n      <Table.Cell>3</Table.Cell>\n      <Table.Cell>Produto teste</Table.Cell>\n      <Table.Cell>John Doe</Table.Cell>\n      <Table.Cell align='right'>R$ 200,20</Table.Cell>\n    </Table.Row>\n  </Table>\n    </Playground>\n    <h2 {...{\n      \"id\": \"tabela-com-paginação\"\n    }}>{`Tabela com paginação`}</h2>\n    <Playground __position={1} __code={'<Table>\\n  <Table.Column field=\\\"id\\\" label=\\\"ID\\\" />\\n  <Table.Column field=\\\"product\\\" label=\\\"Produto\\\" />\\n  <Table.Column field=\\\"owner\\\" label=\\\"Produtor\\\" />\\n  <Table.Column field=\\\"value\\\" label=\\\"Valor\\\" align=\\\"right\\\" />\\n  <Table.Row>\\n    <Table.Cell>1</Table.Cell>\\n    <Table.Cell>Produto teste</Table.Cell>\\n    <Table.Cell>John Doe</Table.Cell>\\n    <Table.Cell align=\\\"right\\\">R$ 120,00</Table.Cell>\\n  </Table.Row>\\n  <Table.Row>\\n    <Table.Cell>2</Table.Cell>\\n    <Table.Cell>Produto teste</Table.Cell>\\n    <Table.Cell>John Doe</Table.Cell>\\n    <Table.Cell align=\\\"right\\\">R$ 100,00</Table.Cell>\\n  </Table.Row>\\n  <Table.Row>\\n    <Table.Cell>3</Table.Cell>\\n    <Table.Cell>Produto teste</Table.Cell>\\n    <Table.Cell>John Doe</Table.Cell>\\n    <Table.Cell align=\\\"right\\\">R$ 200,20</Table.Cell>\\n  </Table.Row>\\n  <Table.Pagination\\n    page={1}\\n    perPage={5}\\n    total={20}\\n    onChangePage={page => console.log(page)}\\n  />\\n</Table>'} __scope={{\n      props,\n      DefaultLayout,\n      Playground,\n      Table,\n      DefaultLayout,\n      _frontmatter\n    }} mdxType=\"Playground\">\n  <Table mdxType=\"Table\">\n    <Table.Column field='id' label='ID' />\n    <Table.Column field='product' label='Produto' />\n    <Table.Column field='owner' label='Produtor' />\n    <Table.Column field='value' label='Valor' align='right' />\n    <Table.Row>\n      <Table.Cell>1</Table.Cell>\n      <Table.Cell>Produto teste</Table.Cell>\n      <Table.Cell>John Doe</Table.Cell>\n      <Table.Cell align='right'>R$ 120,00</Table.Cell>\n    </Table.Row>\n    <Table.Row>\n      <Table.Cell>2</Table.Cell>\n      <Table.Cell>Produto teste</Table.Cell>\n      <Table.Cell>John Doe</Table.Cell>\n      <Table.Cell align='right'>R$ 100,00</Table.Cell>\n    </Table.Row>\n    <Table.Row>\n      <Table.Cell>3</Table.Cell>\n      <Table.Cell>Produto teste</Table.Cell>\n      <Table.Cell>John Doe</Table.Cell>\n      <Table.Cell align='right'>R$ 200,20</Table.Cell>\n    </Table.Row>\n    <Table.Pagination page={1} perPage={5} total={20} onChangePage={page => console.log(page)} />\n  </Table>\n    </Playground>\n    <h2 {...{\n      \"id\": \"tabela-com-ações\"\n    }}>{`Tabela com ações`}</h2>\n    <Playground __position={2} __code={'<Table>\\n  <Table.Column field=\\\"id\\\" label=\\\"ID\\\" />\\n  <Table.Column field=\\\"product\\\" label=\\\"Produto\\\" />\\n  <Table.Column field=\\\"owner\\\" label=\\\"Produtor\\\" />\\n  <Table.Column field=\\\"value\\\" label=\\\"Valor\\\" align=\\\"right\\\" />\\n  <Table.Row data={{ id: 1, product: \\'Produto teste \\' }}>\\n    <Table.Cell>1</Table.Cell>\\n    <Table.Cell>Produto teste</Table.Cell>\\n    <Table.Cell>John Doe</Table.Cell>\\n    <Table.Cell align=\\\"right\\\">R$ 120,00</Table.Cell>\\n  </Table.Row>\\n  <Table.Row data={{ id: 2, product: \\'Produto teste \\' }}>\\n    <Table.Cell>2</Table.Cell>\\n    <Table.Cell>Produto teste</Table.Cell>\\n    <Table.Cell>John Doe</Table.Cell>\\n    <Table.Cell align=\\\"right\\\">R$ 100,00</Table.Cell>\\n  </Table.Row>\\n  <Table.Row data={{ id: 3, product: \\'Produto teste \\' }}>\\n    <Table.Cell>3</Table.Cell>\\n    <Table.Cell>Produto teste</Table.Cell>\\n    <Table.Cell>John Doe</Table.Cell>\\n    <Table.Cell align=\\\"right\\\">R$ 200,20</Table.Cell>\\n    <Table.Actions>\\n      <Table.Option>Ação especial</Table.Option>\\n      <Table.Option>Editar</Table.Option>\\n      <Table.Option>Remover</Table.Option>\\n    </Table.Actions>\\n  </Table.Row>\\n  <Table.Actions align=\\\"right\\\" label=\\\"*\\\">\\n    <Table.Option onClick={row => console.log(row)}>Editar</Table.Option>\\n    <Table.Option>Remover</Table.Option>\\n  </Table.Actions>\\n</Table>'} __scope={{\n      props,\n      DefaultLayout,\n      Playground,\n      Table,\n      DefaultLayout,\n      _frontmatter\n    }} mdxType=\"Playground\">\n  <Table mdxType=\"Table\">\n    <Table.Column field='id' label='ID' />\n    <Table.Column field='product' label='Produto' />\n    <Table.Column field='owner' label='Produtor' />\n    <Table.Column field='value' label='Valor' align='right' />\n    <Table.Row data={{\n          id: 1,\n          product: 'Produto teste '\n        }}>\n      <Table.Cell>1</Table.Cell>\n      <Table.Cell>Produto teste</Table.Cell>\n      <Table.Cell>John Doe</Table.Cell>\n      <Table.Cell align='right'>R$ 120,00</Table.Cell>\n    </Table.Row>\n    <Table.Row data={{\n          id: 2,\n          product: 'Produto teste '\n        }}>\n      <Table.Cell>2</Table.Cell>\n      <Table.Cell>Produto teste</Table.Cell>\n      <Table.Cell>John Doe</Table.Cell>\n      <Table.Cell align='right'>R$ 100,00</Table.Cell>\n    </Table.Row>\n    <Table.Row data={{\n          id: 3,\n          product: 'Produto teste '\n        }}>\n      <Table.Cell>3</Table.Cell>\n      <Table.Cell>Produto teste</Table.Cell>\n      <Table.Cell>John Doe</Table.Cell>\n      <Table.Cell align='right'>R$ 200,20</Table.Cell>\n      <Table.Actions>\n        <Table.Option>Ação especial</Table.Option>\n        <Table.Option>Editar</Table.Option>\n        <Table.Option>Remover</Table.Option>\n      </Table.Actions>\n    </Table.Row>\n    <Table.Actions align='right' label='*'>\n      <Table.Option onClick={row => console.log(row)}>Editar</Table.Option>\n      <Table.Option>Remover</Table.Option>\n    </Table.Actions>\n  </Table>\n    </Playground>\n    <h2 {...{\n      \"id\": \"tabela-com-ordenação\"\n    }}>{`Tabela com ordenação`}</h2>\n    <Playground __position={3} __code={'<Table onSortable={ordenation => console.log(ordenation)}>\\n  <Table.Column field=\\\"id\\\" label=\\\"ID\\\" />\\n  <Table.Column field=\\\"product\\\" label=\\\"Produto\\\" sortable />\\n  <Table.Column field=\\\"owner\\\" label=\\\"Produtor\\\" sortable />\\n  <Table.Column field=\\\"value\\\" label=\\\"Valor\\\" align=\\\"right\\\" />\\n  <Table.Row>\\n    <Table.Cell>1</Table.Cell>\\n    <Table.Cell>Produto teste 1</Table.Cell>\\n    <Table.Cell>John Doe</Table.Cell>\\n    <Table.Cell align=\\\"right\\\">R$ 120,00</Table.Cell>\\n  </Table.Row>\\n  <Table.Row>\\n    <Table.Cell>2</Table.Cell>\\n    <Table.Cell>Produto teste 2</Table.Cell>\\n    <Table.Cell>John Doe</Table.Cell>\\n    <Table.Cell align=\\\"right\\\">R$ 100,00</Table.Cell>\\n  </Table.Row>\\n  <Table.Row>\\n    <Table.Cell>3</Table.Cell>\\n    <Table.Cell>Produto teste 3</Table.Cell>\\n    <Table.Cell>John Doe</Table.Cell>\\n    <Table.Cell align=\\\"right\\\">R$ 200,20</Table.Cell>\\n  </Table.Row>\\n</Table>'} __scope={{\n      props,\n      DefaultLayout,\n      Playground,\n      Table,\n      DefaultLayout,\n      _frontmatter\n    }} mdxType=\"Playground\">\n  <Table onSortable={ordenation => console.log(ordenation)} mdxType=\"Table\">\n    <Table.Column field='id' label='ID' />\n    <Table.Column field='product' label='Produto' sortable />\n    <Table.Column field='owner' label='Produtor' sortable />\n    <Table.Column field='value' label='Valor' align='right' />\n    <Table.Row>\n      <Table.Cell>1</Table.Cell>\n      <Table.Cell>Produto teste 1</Table.Cell>\n      <Table.Cell>John Doe</Table.Cell>\n      <Table.Cell align='right'>R$ 120,00</Table.Cell>\n    </Table.Row>\n    <Table.Row>\n      <Table.Cell>2</Table.Cell>\n      <Table.Cell>Produto teste 2</Table.Cell>\n      <Table.Cell>John Doe</Table.Cell>\n      <Table.Cell align='right'>R$ 100,00</Table.Cell>\n    </Table.Row>\n    <Table.Row>\n      <Table.Cell>3</Table.Cell>\n      <Table.Cell>Produto teste 3</Table.Cell>\n      <Table.Cell>John Doe</Table.Cell>\n      <Table.Cell align='right'>R$ 200,20</Table.Cell>\n    </Table.Row>\n  </Table>\n    </Playground>\n    <h2 {...{\n      \"id\": \"tabela-com-collapse\"\n    }}>{`Tabela com collapse`}</h2>\n    <Playground __position={4} __code={'<Table>\\n  <Table.Column field=\\\"id\\\" label=\\\"ID\\\" />\\n  <Table.Column field=\\\"product\\\" label=\\\"Produto\\\" />\\n  <Table.Column field=\\\"owner\\\" label=\\\"Produtor\\\" />\\n  <Table.Column field=\\\"value\\\" label=\\\"Valor\\\" align=\\\"right\\\" />\\n  <Table.Row>\\n    <Table.Cell>1</Table.Cell>\\n    <Table.Cell>Produto teste</Table.Cell>\\n    <Table.Cell>John Doe</Table.Cell>\\n    <Table.Cell align=\\\"right\\\">R$ 120,00</Table.Cell>\\n  </Table.Row>\\n  <Table.Row data={{ id: 2, product: \\'Produto teste\\' }}>\\n    <Table.Cell>2</Table.Cell>\\n    <Table.Cell>Produto teste</Table.Cell>\\n    <Table.Cell>John Doe</Table.Cell>\\n    <Table.Cell align=\\\"right\\\">R$ 100,00</Table.Cell>\\n    <Table.Collapse>\\n      <Table.Column field=\\\"date\\\" label=\\\"Data\\\" />\\n      <Table.Column field=\\\"sales\\\" label=\\\"Vendas\\\" />\\n      <Table.Row>\\n        <Table.Cell>29/03</Table.Cell>\\n        <Table.Cell>20 vendas</Table.Cell>\\n      </Table.Row>\\n      <Table.Row>\\n        <Table.Cell>28/03</Table.Cell>\\n        <Table.Cell>170 vendas</Table.Cell>\\n      </Table.Row>\\n    </Table.Collapse>\\n  </Table.Row>\\n  <Table.Row>\\n    <Table.Cell>3</Table.Cell>\\n    <Table.Cell>Produto teste</Table.Cell>\\n    <Table.Cell>John Doe</Table.Cell>\\n    <Table.Cell align=\\\"right\\\">R$ 200,20</Table.Cell>\\n  </Table.Row>\\n</Table>'} __scope={{\n      props,\n      DefaultLayout,\n      Playground,\n      Table,\n      DefaultLayout,\n      _frontmatter\n    }} mdxType=\"Playground\">\n  <Table mdxType=\"Table\">\n    <Table.Column field='id' label='ID' />\n    <Table.Column field='product' label='Produto' />\n    <Table.Column field='owner' label='Produtor' />\n    <Table.Column field='value' label='Valor' align='right' />\n    <Table.Row>\n      <Table.Cell>1</Table.Cell>\n      <Table.Cell>Produto teste</Table.Cell>\n      <Table.Cell>John Doe</Table.Cell>\n      <Table.Cell align='right'>R$ 120,00</Table.Cell>\n    </Table.Row>\n    <Table.Row data={{\n          id: 2,\n          product: 'Produto teste'\n        }}>\n      <Table.Cell>2</Table.Cell>\n      <Table.Cell>Produto teste</Table.Cell>\n      <Table.Cell>John Doe</Table.Cell>\n      <Table.Cell align='right'>R$ 100,00</Table.Cell>\n      <Table.Collapse>\n        <Table.Column field='date' label='Data' />\n        <Table.Column field='sales' label='Vendas' />\n        <Table.Row>\n          <Table.Cell>29/03</Table.Cell>\n          <Table.Cell>20 vendas</Table.Cell>\n        </Table.Row>\n        <Table.Row>\n          <Table.Cell>28/03</Table.Cell>\n          <Table.Cell>170 vendas</Table.Cell>\n        </Table.Row>\n      </Table.Collapse>\n    </Table.Row>\n    <Table.Row>\n      <Table.Cell>3</Table.Cell>\n      <Table.Cell>Produto teste</Table.Cell>\n      <Table.Cell>John Doe</Table.Cell>\n      <Table.Cell align='right'>R$ 200,20</Table.Cell>\n    </Table.Row>\n  </Table>\n    </Playground>\n    <h2 {...{\n      \"id\": \"propriedades-da-tablecolumn\"\n    }}>{`Propriedades da Table.Column`}</h2>\n    <p>{`Usando tabela do próprio markdown`}</p>\n    <table>\n      <thead parentName=\"table\">\n        <tr parentName=\"thead\">\n          <th parentName=\"tr\" {...{\n            \"align\": null\n          }}>{`prop`}</th>\n          <th parentName=\"tr\" {...{\n            \"align\": null\n          }}>{`tipo`}</th>\n          <th parentName=\"tr\" {...{\n            \"align\": null\n          }}>{`obrigatório`}</th>\n          <th parentName=\"tr\" {...{\n            \"align\": null\n          }}>{`padrão`}</th>\n          <th parentName=\"tr\" {...{\n            \"align\": null\n          }}>{`descrição`}</th>\n        </tr>\n      </thead>\n      <tbody parentName=\"table\">\n        <tr parentName=\"tbody\">\n          <td parentName=\"tr\" {...{\n            \"align\": null\n          }}>{`field`}</td>\n          <td parentName=\"tr\" {...{\n            \"align\": null\n          }}><inlineCode parentName=\"td\">{`string`}</inlineCode></td>\n          <td parentName=\"tr\" {...{\n            \"align\": null\n          }}>{`true`}</td>\n          <td parentName=\"tr\" {...{\n            \"align\": null\n          }}>{`-`}</td>\n          <td parentName=\"tr\" {...{\n            \"align\": null\n          }}>{`Chave única.`}</td>\n        </tr>\n        <tr parentName=\"tbody\">\n          <td parentName=\"tr\" {...{\n            \"align\": null\n          }}>{`label`}</td>\n          <td parentName=\"tr\" {...{\n            \"align\": null\n          }}><inlineCode parentName=\"td\">{`React.ReactNode`}</inlineCode></td>\n          <td parentName=\"tr\" {...{\n            \"align\": null\n          }}>{`true`}</td>\n          <td parentName=\"tr\" {...{\n            \"align\": null\n          }}>{`-`}</td>\n          <td parentName=\"tr\" {...{\n            \"align\": null\n          }}>{`-`}</td>\n        </tr>\n        <tr parentName=\"tbody\">\n          <td parentName=\"tr\" {...{\n            \"align\": null\n          }}>{`width`}</td>\n          <td parentName=\"tr\" {...{\n            \"align\": null\n          }}><inlineCode parentName=\"td\">{`number`}</inlineCode></td>\n          <td parentName=\"tr\" {...{\n            \"align\": null\n          }}>{`false`}</td>\n          <td parentName=\"tr\" {...{\n            \"align\": null\n          }}>{`-`}</td>\n          <td parentName=\"tr\" {...{\n            \"align\": null\n          }}>{`-`}</td>\n        </tr>\n        <tr parentName=\"tbody\">\n          <td parentName=\"tr\" {...{\n            \"align\": null\n          }}>{`align`}</td>\n          <td parentName=\"tr\" {...{\n            \"align\": null\n          }}><inlineCode parentName=\"td\">{`ITableAlign`}</inlineCode></td>\n          <td parentName=\"tr\" {...{\n            \"align\": null\n          }}>{`false`}</td>\n          <td parentName=\"tr\" {...{\n            \"align\": null\n          }}><inlineCode parentName=\"td\">{`left`}</inlineCode></td>\n          <td parentName=\"tr\" {...{\n            \"align\": null\n          }}>{`-`}</td>\n        </tr>\n        <tr parentName=\"tbody\">\n          <td parentName=\"tr\" {...{\n            \"align\": null\n          }}>{`sortable`}</td>\n          <td parentName=\"tr\" {...{\n            \"align\": null\n          }}><inlineCode parentName=\"td\">{`boolean`}</inlineCode></td>\n          <td parentName=\"tr\" {...{\n            \"align\": null\n          }}>{`false`}</td>\n          <td parentName=\"tr\" {...{\n            \"align\": null\n          }}><inlineCode parentName=\"td\">{`false`}</inlineCode></td>\n          <td parentName=\"tr\" {...{\n            \"align\": null\n          }}>{`Quando `}<inlineCode parentName=\"td\">{`true`}</inlineCode>{`, ao clicar na coluna, chama a função`}<inlineCode parentName=\"td\">{` onSortable`}</inlineCode>{` passando o `}<inlineCode parentName=\"td\">{`field`}</inlineCode>{` e o sort.`}</td>\n        </tr>\n      </tbody>\n    </table>\n\n    </MDXLayout>;\n}\n\n;\nMDXContent.isMDXComponent = true;"}}